x4i/__init__.py
x4i/abundance.py
x4i/endl_Z.py
x4i/exfor_column_transformer.py
x4i/exfor_dataset.py
x4i/exfor_dicts.py
x4i/exfor_entry.py
x4i/exfor_exceptions.py
x4i/exfor_field.py
x4i/exfor_grammars.py
x4i/exfor_manager.py
x4i/exfor_particle.py
x4i/exfor_paths.py
x4i/exfor_reactions.py
x4i/exfor_reference.py
x4i/exfor_section.py
x4i/exfor_subentry.py
x4i/exfor_units.py
x4i/exfor_utilities.py
x4i/cli/__init__.py
x4i/cli/check_exfor.py
x4i/cli/exfor2json.py
x4i/cli/get_exfor_entry.py
x4i/cli/install_exfor_db.py
x4i/cli/setup_exfor_db_index.py
x4i/data/x4doi.txt
x4i/dicts/dict_arc_all.json
x4i/dicts/exfor-pint-definitions.txt
x4i/dicts/exfor_units.csv
x4i/dicts/make_exfor_unit_csv.py
x4i-1.0.5.dev0.dist-info/licenses/LICENSE.txt
x4i-1.0.5.dev0.dist-info/METADATA
x4i-1.0.5.dev0.dist-info/WHEEL
x4i-1.0.5.dev0.dist-info/entry_points.txt
x4i-1.0.5.dev0.dist-info/top_level.txt
x4i-1.0.5.dev0.dist-info/RECORD
