Metadata-Version: 2.4
Name: x4i
Version: 1.0.5.dev0
Summary: A "simple" python interface to the EXFOR library
Author-email: "David A. Brown" <dbrown@bnl.gov>
Maintainer-email: "David A. Brown" <dbrown@bnl.gov>
License: **** x4i.pyparsing.py LICENSE
Project-URL: Homepage, https://github.com/brown170/x4i
Project-URL: Documentation, https://github.com/brown170/x4i/blob/main/doc/x4i/user-guide/x4i.pdf
Project-URL: Repository, https://github.com/brown170/x4i.git
Project-URL: Bug Tracker, https://github.com/brown170/x4i/issues
Project-URL: Changelog, https://github.com/brown170/x4i/blob/main/CHANGES.txt
Keywords: EXFOR,nuclear reaction data
Classifier: Development Status :: 5 - Production/Stable
Classifier: Programming Language :: Python
Requires-Python: >=3.0
License-File: LICENSE.txt
Requires-Dist: numpy>1.2
Requires-Dist: pint>0.20
Requires-Dist: pandas>2
Requires-Dist: pint-pandas
Requires-Dist: pyparsing>=3.1.2
Requires-Dist: bidict
Requires-Dist: tabulate>=0.9
Requires-Dist: packaging
Provides-Extra: test
Requires-Dist: pytest>8.2; extra == "test"
Dynamic: license-file
